{"data":{"product":{"id":"Shopify__Product__Z2lkOi8vc2hvcGlmeS9Qcm9kdWN0LzE3OTE4ODM1NzUzNDU=","shopifyId":"Z2lkOi8vc2hvcGlmeS9Qcm9kdWN0LzE3OTE4ODM1NzUzNDU=","productType":"Chenille Patch","title":"Pride Pennant Chenille Patch","handle":"oxford-pennant-rainbow-pennant-chenille-patch","description":"Oxford Pennant - Pride Pennant Chenille Patch Size: 4.5\" x 2.5\" Color: Purple, blue, green, yellow, orange, red, and black In celebration of Pride month, 20% of all June Pride Collection proceeds will benefit the Pride Center of WNY","descriptionHtml":"<meta charset=\"utf-8\">\n<p><strong><em><span style=\"color: #ff2a00;\"></span></em></strong><span style=\"color: #ff2a00;\"><strong></strong></span>Oxford Pennant - Pride Pennant Chenille Patch<br></p>\n<p>Size: 4.5\" x 2.5\"</p>\n<p>Color: Purple, blue, green, yellow, orange, red, and black </p>\n<p><meta charset=\"utf-8\"><span>In celebration of Pride month, 20% of all June </span><em>Pride Collection</em><span> proceeds will benefit the Pride Center of WNY</span></p>","availableForSale":true,"options":[{"name":"Title","values":["Default Title"]}],"images":[{"originalSrc":"https://cdn.shopify.com/s/files/1/0329/1313/products/OP-Chenille-PridePennant-Full.jpg?v=1543428974","altText":null},{"originalSrc":"https://cdn.shopify.com/s/files/1/0329/1313/products/OP-Chenille-PridePennant-Detail.jpg?v=1543428978","altText":null}],"priceRange":{"maxVariantPrice":{"amount":"12.0"},"minVariantPrice":{"amount":"12.0"}},"tags":["Chenille","HOL 2020 stock update","Patch","Pride","Pride '19"],"variants":[{"shopifyId":"Z2lkOi8vc2hvcGlmeS9Qcm9kdWN0VmFyaWFudC8xNDI5OTU1NzcyNDIwOQ==","price":"12.00","selectedOptions":[{"name":"Title","value":"Default Title"}],"image":{"originalSrc":"https://cdn.shopify.com/s/files/1/0329/1313/products/OP-Chenille-PridePennant-Full.jpg?v=1543428974"}}]}},"pageContext":{"productId":"Shopify__Product__Z2lkOi8vc2hvcGlmeS9Qcm9kdWN0LzE3OTE4ODM1NzUzNDU=","productType":"Chenille Patch"}}