{"data":{"product":{"id":"Shopify__Product__Z2lkOi8vc2hvcGlmeS9Qcm9kdWN0LzE3OTI0Nzg0NzgzODU=","shopifyId":"Z2lkOi8vc2hvcGlmeS9Qcm9kdWN0LzE3OTI0Nzg0NzgzODU=","productType":"Pennant","title":"Ever Upward Pennant • United By Blue x True Hand Society x Oxford Pennant Original","handle":"ever-upward-pennant-united-by-blue-x-true-hand-society-x-oxford-pennant-original","description":"Part of a collaboration with United By Blue, featuring New York City-inspired designs by True Hand Society. Size: 9\" x 27\" Material: Cut-and-sewn wool felt, screen-printed design Color: Gold","descriptionHtml":"<p><meta charset=\"utf-8\">Part of a collaboration with <a href=\"https://unitedbyblue.com/\">United By Blue</a>, featuring New York City-inspired designs by <a href=\"https://truehandsociety.com/\">True Hand Society</a>.</p>\n<p>Size: 9\" x 27\"</p>\n<p><span data-sheets-value='{\"1\":2,\"2\":\"Still like to make a big racket, but our 7-foot flag is a bit much? Try this custom Raise Hell, Kid mini Championship Banner instead. Screen-printed lettering.\"}' data-sheets-userformat='{\"2\":769,\"3\":[null,0],\"11\":4,\"12\":0}'>Material: Cut-and-sewn wool felt, screen-printed design</span></p>\n<p><span data-sheets-value='{\"1\":2,\"2\":\"Still like to make a big racket, but our 7-foot flag is a bit much? Try this custom Raise Hell, Kid mini Championship Banner instead. Screen-printed lettering.\"}' data-sheets-userformat='{\"2\":769,\"3\":[null,0],\"11\":4,\"12\":0}'>Color: Gold </span></p>","availableForSale":true,"options":[{"name":"Title","values":["Default Title"]}],"images":[{"originalSrc":"https://cdn.shopify.com/s/files/1/0329/1313/products/EverUpward-Pennant-Full.jpg?v=1543592237","altText":null}],"priceRange":{"maxVariantPrice":{"amount":"25.0"},"minVariantPrice":{"amount":"25.0"}},"tags":["Best Seller","Collaboration","Gift","gift ideas","New York City","NYC","UBB x THS x OP"],"variants":[{"shopifyId":"Z2lkOi8vc2hvcGlmeS9Qcm9kdWN0VmFyaWFudC8xNDMwMjI5ODkzMTI0OQ==","price":"25.00","selectedOptions":[{"name":"Title","value":"Default Title"}],"image":{"originalSrc":"https://cdn.shopify.com/s/files/1/0329/1313/products/EverUpward-Pennant-Full.jpg?v=1543592237"}}]}},"pageContext":{"productId":"Shopify__Product__Z2lkOi8vc2hvcGlmeS9Qcm9kdWN0LzE3OTI0Nzg0NzgzODU=","productType":"Pennant"}}