{"data":{"product":{"id":"Shopify__Product__Z2lkOi8vc2hvcGlmeS9Qcm9kdWN0LzY1NTk1NTg2OTcwMDk=","shopifyId":"Z2lkOi8vc2hvcGlmeS9Qcm9kdWN0LzY1NTk1NTg2OTcwMDk=","productType":"Vintage Framed Pennant","title":"Vintage Sabres Think Stanley Cup - Framed","handle":"vintage-sabres-think-stanley-cup-framed","description":"Size: approx. 16\" x 33\" *Price includes UPS ground shipping within the Continental US. International customers, please contact us for more info. All framed vintage pennants are final sale.","descriptionHtml":"<p>Size: approx. 16\" x 33\"</p>\n\n<p>*Price includes UPS ground shipping within the Continental US. International customers, please contact us for more info. All framed vintage pennants are final sale.</p>","availableForSale":true,"options":[{"name":"Title","values":["Default title"]}],"images":[{"originalSrc":"https://cdn.shopify.com/s/files/1/0329/1313/products/sabres.jpg?v=1618329139","altText":null},{"originalSrc":"https://cdn.shopify.com/s/files/1/0329/1313/products/sabres-detail.jpg?v=1618329139","altText":"Lifestyle product shot"},{"originalSrc":"https://cdn.shopify.com/s/files/1/0329/1313/products/emblem-black.png?v=1618329139","altText":null},{"originalSrc":"https://cdn.shopify.com/s/files/1/0329/1313/products/backing_8c87071b-4dbd-4945-b60f-1a678d5b50b1.png?v=1618329139","altText":null}],"priceRange":{"maxVariantPrice":{"amount":"250.0"},"minVariantPrice":{"amount":"250.0"}},"tags":["Buffalo","New York","NHL","Sabres","Stanley Cup","Vintage","Vintage Frame","Vintage Framed Pennant"],"variants":[{"shopifyId":"Z2lkOi8vc2hvcGlmeS9Qcm9kdWN0VmFyaWFudC8zOTI5ODAzNTQ4MjY3Mw==","price":"250.00","selectedOptions":[{"name":"Title","value":"Default title"}],"image":{"originalSrc":"https://cdn.shopify.com/s/files/1/0329/1313/products/sabres.jpg?v=1618329139"}}]}},"pageContext":{"productId":"Shopify__Product__Z2lkOi8vc2hvcGlmeS9Qcm9kdWN0LzY1NTk1NTg2OTcwMDk=","productType":"Vintage Framed Pennant"}}