{"data":{"product":{"id":"Shopify__Product__Z2lkOi8vc2hvcGlmeS9Qcm9kdWN0LzQzNTg4NzgwMzYwMTc=","shopifyId":"Z2lkOi8vc2hvcGlmeS9Qcm9kdWN0LzQzNTg4NzgwMzYwMTc=","productType":"Apparel - Chainstitching","title":"Blank Vintage Denim Vest - Women's Small","handle":"blank-vintage-denim-jacket-mens-x-small-2","description":"Vintage 1980's Levi's Cutoff Vest - Women's Small Measurements: 1/2 chest - 19.5\" Length - 20\" Shoulder - 18\"","descriptionHtml":"<meta charset=\"utf-8\">\n<p><span>Vintage 1980's Levi's Cutoff Vest - Women's Small</span></p>\n<p><span></span>Measurements:</p>\n<p>1/2 chest - 19.5\"</p>\n<p>Length - 20\"</p>\n<p>Shoulder - 18\" </p>","availableForSale":true,"options":[{"name":"Title","values":["Default Title"]}],"images":[{"originalSrc":"https://cdn.shopify.com/s/files/1/0329/1313/products/23_front.png?v=1573665253","altText":null},{"originalSrc":"https://cdn.shopify.com/s/files/1/0329/1313/products/23_back.png?v=1573665253","altText":null},{"originalSrc":"https://cdn.shopify.com/s/files/1/0329/1313/products/23_detail3.png?v=1573665253","altText":null},{"originalSrc":"https://cdn.shopify.com/s/files/1/0329/1313/products/23_detail.png?v=1573665253","altText":null},{"originalSrc":"https://cdn.shopify.com/s/files/1/0329/1313/products/23_detail2.png?v=1573665253","altText":null}],"priceRange":{"maxVariantPrice":{"amount":"80.0"},"minVariantPrice":{"amount":"80.0"}},"tags":["Blank","Chainstitch","Chainstitching","Customizable","Denim Jacket","Jacket","Vest"],"variants":[{"shopifyId":"Z2lkOi8vc2hvcGlmeS9Qcm9kdWN0VmFyaWFudC8zMTE5NTg1ODQ2ODkxMw==","price":"80.00","selectedOptions":[{"name":"Title","value":"Default Title"}],"image":{"originalSrc":"https://cdn.shopify.com/s/files/1/0329/1313/products/23_front.png?v=1573665253"}}]}},"pageContext":{"productId":"Shopify__Product__Z2lkOi8vc2hvcGlmeS9Qcm9kdWN0LzQzNTg4NzgwMzYwMTc=","productType":"Apparel - Chainstitching"}}