{"data":{"product":{"id":"Shopify__Product__Z2lkOi8vc2hvcGlmeS9Qcm9kdWN0LzQ3ODg2NjM2NDgzMDU=","shopifyId":"Z2lkOi8vc2hvcGlmeS9Qcm9kdWN0LzQ3ODg2NjM2NDgzMDU=","productType":"Vintage Framed Pennant","title":"Vintage California Bear Pennant - Framed","handle":"vintage-california-bear-pennant-framed","description":"Size: approx. 16.25\" x 38.25\" *Price includes UPS ground shipping within the Continental US. International customers, please contact us for more info. All framed vintage pennants are final sale.","descriptionHtml":"<p>Size: approx. 16.25\" x 38.25\"</p>\n<p>*Price includes UPS ground shipping within the Continental US. International customers, please contact us for more info. All framed vintage pennants are final sale. </p>","availableForSale":true,"options":[{"name":"Title","values":["Default title"]}],"images":[{"originalSrc":"https://cdn.shopify.com/s/files/1/0329/1313/products/california.png?v=1604516769","altText":null},{"originalSrc":"https://cdn.shopify.com/s/files/1/0329/1313/products/california_detail.png?v=1604516769","altText":null},{"originalSrc":"https://cdn.shopify.com/s/files/1/0329/1313/products/emblemblack_191c547c-0ac3-4912-8c3a-3c9abfe252ef.jpg?v=1604516769","altText":null},{"originalSrc":"https://cdn.shopify.com/s/files/1/0329/1313/products/black.png?v=1604516769","altText":null}],"priceRange":{"maxVariantPrice":{"amount":"300.0"},"minVariantPrice":{"amount":"300.0"}},"tags":["Bear","Cali","California","Vintage","Vintage Frame","Vintage Framed Pennant","West Coast"],"variants":[{"shopifyId":"Z2lkOi8vc2hvcGlmeS9Qcm9kdWN0VmFyaWFudC8zMjUxMDc3NjE4MDc4NQ==","price":"300.00","selectedOptions":[{"name":"Title","value":"Default title"}],"image":{"originalSrc":"https://cdn.shopify.com/s/files/1/0329/1313/products/california.png?v=1604516769"}}]}},"pageContext":{"productId":"Shopify__Product__Z2lkOi8vc2hvcGlmeS9Qcm9kdWN0LzQ3ODg2NjM2NDgzMDU=","productType":"Vintage Framed Pennant"}}